Metadata-Version: 2.1
Name: gap-loader
Version: 0.3
Summary: Import hook for GAP files in SAGE math.
Home-page: http://github.com/jorants/gap-loader
Author: Joran van Apeldoorn (Control-K)
Author-email: jorants@gmail.com
License: MIT
Platform: UNKNOWN
Classifier: License :: OSI Approved :: MIT License
Classifier: Programming Language :: Python :: 2.7
